aspy/__init__.py
aspy-0.4.2.dist-info/DESCRIPTION.rst
aspy-0.4.2.dist-info/METADATA
aspy-0.4.2.dist-info/RECORD
aspy-0.4.2.dist-info/WHEEL
aspy-0.4.2.dist-info/metadata.json
aspy-0.4.2.dist-info/top_level.txt
