Metadata-Version: 2.0
Name: aspy
Version: 0.4.2
Summary: An activity streams 2 library
Home-page: https://gitlab.com/alantrick/aspy
Author: Alan Trick
Author-email: me@alantrick.ca
License: LGPL3+
Project-URL: Bug Tracker, https://gitlab.com/alantrick/aspy/issues
Project-URL: Documentation, http://aspy.readthedocs.io/en/latest/
Project-URL: Source Code, https://gitlab.com/alantrick/aspy
Keywords: activity-feed,activity-streams,social
Platform: UNKNOWN
Classifier: Development Status :: 2 - Pre-Alpha
Classifier: Environment :: Web Environment
Classifier: Intended Audience :: Developers
Classifier: License :: OSI Approved :: GNU Lesser General Public License v3 or later (LGPLv3+)
Classifier: Operating System :: OS Independent
Classifier: Programming Language :: Python
Classifier: Programming Language :: Python :: 3.6
Classifier: Topic :: Utilities
Requires-Python: >=3.6
Provides-Extra: test
Requires-Dist: isodate
Provides-Extra: test
Requires-Dist: pytest; extra == 'test'
Requires-Dist: pytest-cov; extra == 'test'
Requires-Dist: pytest-pythonpath; extra == 'test'
Requires-Dist: tox; extra == 'test'
